noti_sdk_py/__init__.py
noti_sdk_py/api/__init__.py
noti_sdk_py/api/client.py
noti_sdk_py/api/endpoints/__init__.py
noti_sdk_py/api/endpoints/bulk.py
noti_sdk_py/api/endpoints/chats.py
noti_sdk_py/api/endpoints/chatting.py
noti_sdk_py/api/endpoints/contacts.py
noti_sdk_py/api/endpoints/profile.py
noti_sdk_py/api/endpoints/sessions.py
noti_sdk_py/api/endpoints/status.py
noti_sdk_py/utils/__init__.py
noti_sdk_py/utils/request.py
noti_sdk_py-1.0.1.dist-info/licenses/LICENSE
noti_sdk_py-1.0.1.dist-info/METADATA
noti_sdk_py-1.0.1.dist-info/WHEEL
noti_sdk_py-1.0.1.dist-info/top_level.txt
noti_sdk_py-1.0.1.dist-info/RECORD
