Metadata-Version: 2.4
Name: noti-sdk-py
Version: 1.0.1
Summary: Lightweight Python SDK for WhatsApp messaging and bulk messaging via the Notibuzz Cloud REST API.
Home-page: https://github.com/notibuzzcloud/noti-sdk-py
Author: Diego Quiroz Ramirez - CEO NotiBuzz Cloud
Author-email: 
License: MIT
Project-URL: Homepage, https://github.com/notibuzzcloud/noti-sdk-py
Project-URL: Documentation, https://github.com/notibuzzcloud/noti-sdk-py#readme
Project-URL: Repository, https://github.com/notibuzzcloud/noti-sdk-py.git
Project-URL: Bug Tracker, https://github.com/notibuzzcloud/noti-sdk-py/issues
Keywords: notibuzz,sdk,whatsapp,whatsapp-messages,bulk-messaging,messaging,api,notifications,rest-api,saas,notibuzz,notibuzz-cloud,notibuzz-sdk,notibuzz-cloud-sdk,automation
Classifier: Development Status :: 4 - Beta
Classifier: Intended Audience :: Developers
Classifier: License :: OSI Approved :: MIT License
Classifier: Programming Language :: Python :: 3
Classifier: Programming Language :: Python :: 3.8
Classifier: Programming Language :: Python :: 3.9
Classifier: Programming Language :: Python :: 3.10
Classifier: Programming Language :: Python :: 3.11
Classifier: Programming Language :: Python :: 3.12
Classifier: Topic :: Software Development :: Libraries :: Python Modules
Classifier: Topic :: Communications :: Chat
Requires-Python: >=3.8
License-File: LICENSE
Requires-Dist: requests>=2.28.0
Dynamic: home-page
Dynamic: license-file
Dynamic: requires-python
